symphony_duplicates/__init__.py
symphony_duplicates/_frontend.py
symphony_duplicates/_version.py
symphony_duplicates/widget.py
symphony_duplicates/labextension/build_log.json
symphony_duplicates/labextension/package.json
symphony_duplicates/labextension/static/lib_index_js.2b46154e920623a54cc8.js
symphony_duplicates/labextension/static/lib_index_js.2b46154e920623a54cc8.js.map
symphony_duplicates/labextension/static/lib_index_js.40fa491aeb1de93bb6e6.js
symphony_duplicates/labextension/static/lib_index_js.40fa491aeb1de93bb6e6.js.map
symphony_duplicates/labextension/static/remoteEntry.8ae2e0254da4ef432464.js
symphony_duplicates/labextension/static/remoteEntry.8ae2e0254da4ef432464.js.map
symphony_duplicates/labextension/static/remoteEntry.b6b00b75192667ac10b7.js
symphony_duplicates/labextension/static/remoteEntry.b6b00b75192667ac10b7.js.map
symphony_duplicates/labextension/static/style.js
symphony_duplicates/nbextension/extension.js
symphony_duplicates/nbextension/index.js
symphony_duplicates/standalone/widgets/SymphonyDuplicates.js
symphony_duplicates/standalone/widgets/SymphonyDuplicates.js.map
symphony_duplicates-1.0.2.data/data/etc/jupyter/nbconfig/notebook.d/symphony_duplicates.json
symphony_duplicates-1.0.2.data/data/share/jupyter/labextensions/symphony-duplicates/build_log.json
symphony_duplicates-1.0.2.data/data/share/jupyter/labextensions/symphony-duplicates/install.json
symphony_duplicates-1.0.2.data/data/share/jupyter/labextensions/symphony-duplicates/package.json
symphony_duplicates-1.0.2.data/data/share/jupyter/labextensions/symphony-duplicates/static/lib_index_js.40fa491aeb1de93bb6e6.js
symphony_duplicates-1.0.2.data/data/share/jupyter/labextensions/symphony-duplicates/static/lib_index_js.40fa491aeb1de93bb6e6.js.map
symphony_duplicates-1.0.2.data/data/share/jupyter/labextensions/symphony-duplicates/static/remoteEntry.b6b00b75192667ac10b7.js
symphony_duplicates-1.0.2.dist-info/LICENSE.txt
symphony_duplicates-1.0.2.dist-info/METADATA
symphony_duplicates-1.0.2.dist-info/WHEEL
symphony_duplicates-1.0.2.dist-info/top_level.txt
symphony_duplicates-1.0.2.dist-info/RECORD
